data_gradients/__init__.py
data_gradients/requirements.txt
data_gradients/assets/__init__.py
data_gradients/assets/assets_container.py
data_gradients/assets/css/test.css
data_gradients/assets/html/basic_info_fe.html
data_gradients/assets/html/basic_info_fe_classification.html
data_gradients/assets/html/doc_template.html
data_gradients/assets/html/test.html
data_gradients/assets/images/chart_demo.png
data_gradients/assets/images/info.png
data_gradients/assets/images/logo.png
data_gradients/assets/images/warning.png
data_gradients/assets/text/lorem_ipsum.txt
data_gradients/assets/text/test.txt
data_gradients/common/__init__.py
data_gradients/common/decorators/__init__.py
data_gradients/common/decorators/decorators.py
data_gradients/common/factories/__init__.py
data_gradients/common/factories/base_factory.py
data_gradients/common/factories/feature_extractors_factory.py
data_gradients/common/factories/list_factory.py
data_gradients/common/registry/__init__.py
data_gradients/common/registry/registry.py
data_gradients/config/__init__.py
data_gradients/config/classification.yaml
data_gradients/config/detection.yaml
data_gradients/config/segmentation.yaml
data_gradients/config/utils.py
data_gradients/dataset_adapters/__init__.py
data_gradients/dataset_adapters/base_adapter.py
data_gradients/dataset_adapters/classification_adapter.py
data_gradients/dataset_adapters/detection_adapter.py
data_gradients/dataset_adapters/segmentation_adapter.py
data_gradients/dataset_adapters/utils.py
data_gradients/dataset_adapters/config/__init__.py
data_gradients/dataset_adapters/config/caching_utils.py
data_gradients/dataset_adapters/config/data_config.py
data_gradients/dataset_adapters/config/questions.py
data_gradients/dataset_adapters/config/typing_utils.py
data_gradients/dataset_adapters/formatters/__init__.py
data_gradients/dataset_adapters/formatters/base.py
data_gradients/dataset_adapters/formatters/classification.py
data_gradients/dataset_adapters/formatters/detection.py
data_gradients-0.3.2.dist-info/LICENSE.md
data_gradients-0.3.2.dist-info/METADATA
data_gradients-0.3.2.dist-info/WHEEL
data_gradients-0.3.2.dist-info/top_level.txt
data_gradients-0.3.2.dist-info/RECORD
