Metadata-Version: 2.1
Name: data-gradients
Version: 0.3.2
Summary: DataGradients
Home-page: https://github.com/Deci-AI/data-gradients
Author: Deci AI
Author-email: rnd@deci.ai
Keywords: Deci,AI,Data,Deep Learning,Computer Vision,PyTorch
License-File: LICENSE.md
Requires-Dist: hydra-core >=1.2.0
Requires-Dist: omegaconf >=2.2.3
Requires-Dist: pygments >=2.13.0
Requires-Dist: tqdm >=4.64.1
Requires-Dist: platformdirs >=2.5.2
Requires-Dist: opencv-python
Requires-Dist: Pillow
Requires-Dist: tensorboard
Requires-Dist: torch
Requires-Dist: torchvision
Requires-Dist: numpy
Requires-Dist: matplotlib
Requires-Dist: scipy
Requires-Dist: rapidfuzz
Requires-Dist: coverage ~=5.3.1
Requires-Dist: seaborn
Requires-Dist: xhtml2pdf ==0.2.11
Requires-Dist: jinja2
Requires-Dist: imagededup
